{"version":1,"resource":"file:///home/burgos/code/boz.app/src/contexts/departmentsContext.tsx","entries":[{"id":"9sYv.tsx","timestamp":1691746813328},{"id":"2nRP.tsx","timestamp":1691747059111},{"id":"sDgt.tsx","timestamp":1691756159343},{"id":"L8uW.tsx","timestamp":1691763254045},{"id":"Z8lO.tsx","timestamp":1691763465520},{"id":"mhbR.tsx","timestamp":1691763484681},{"id":"Hf0E.tsx","timestamp":1692139996928},{"id":"J3mo.tsx","timestamp":1692140084867},{"id":"oOkw.tsx","timestamp":1692140403059},{"id":"2tLC.tsx","timestamp":1692202064333},{"id":"i9t8.tsx","timestamp":1692223487153}]}