{"version":1,"resource":"file:///home/burgos/code/AgenciaZOP/tec.agro/src/pages/Crops/NearYouList.tsx","entries":[{"id":"slOl.tsx","timestamp":1689703470110},{"id":"y0LL.tsx","timestamp":1689703973807},{"id":"pfXc.tsx","timestamp":1689704241668},{"id":"STTd.tsx","timestamp":1689704292090},{"id":"gH7c.tsx","timestamp":1689704319023},{"id":"vLk8.tsx","timestamp":1689704346620},{"id":"aQH4.tsx","source":"undoRedo.source","timestamp":1689704350756},{"id":"o6iB.tsx","timestamp":1689704365000},{"id":"zWWn.tsx","timestamp":1689704378145},{"id":"kgr0.tsx","source":"undoRedo.source","timestamp":1689704381377},{"id":"bA0J.tsx","timestamp":1689704387953},{"id":"FF5u.tsx","timestamp":1689704411062},{"id":"8e0y.tsx","timestamp":1689705178576},{"id":"st4U.tsx","timestamp":1689705246579},{"id":"JCJv.tsx","timestamp":1689705334162},{"id":"FAd3.tsx","timestamp":1689717535827},{"id":"mGUT.tsx","timestamp":1689718853415},{"id":"ZMBd.tsx","timestamp":1689774754609},{"id":"VqAo.tsx","source":"Renaming nextLocation to list","timestamp":1689795551899},{"id":"hGJp.tsx","timestamp":1689799190659},{"id":"aUX4.tsx","timestamp":1689799200771},{"id":"C9lO.tsx","timestamp":1689799216804},{"id":"HbPI.tsx","timestamp":1689801030035}]}