{"version":1,"resource":"file:///home/burgos/code/AgenciaZOP/tec.agro/src/contexts/businessesContext.tsx","entries":[{"id":"Ztvb.tsx","timestamp":1689886306971},{"id":"DIVv.tsx","timestamp":1689887003718},{"id":"UvKs.tsx","timestamp":1689889297269},{"id":"Ta6q.tsx","timestamp":1689889742132},{"id":"H5CV.tsx","timestamp":1689892169805},{"id":"1by8.tsx","timestamp":1689892476010},{"id":"w11p.tsx","timestamp":1689933135445},{"id":"DJrd.tsx","timestamp":1690569647053},{"id":"V786.tsx","timestamp":1690569709708},{"id":"Yugw.tsx","timestamp":1690569750409}]}