{"version":1,"resource":"file:///home/burgos/code/AgenciaZOP/tec.agro/src/definitions/subaccount.d.ts","entries":[{"id":"A6r8.ts","timestamp":1690220031963},{"id":"h3SA.ts","timestamp":1690234252077},{"id":"Y3ix.ts","timestamp":1690405214156},{"id":"pA5P.ts","timestamp":1690405316423},{"id":"tSc3.ts","timestamp":1690405598473},{"id":"gs1Z.ts","timestamp":1690405702485},{"id":"o1jG.ts","timestamp":1690405715937},{"id":"ZDam.ts","timestamp":1690405741578},{"id":"QjkL.ts","timestamp":1690407636104},{"id":"SeeP.ts","timestamp":1690408368089},{"id":"BROF.ts","timestamp":1690408534599}]}